sc_entsoe/__init__.py
sc_entsoe/__init__.pyi
sc_entsoe/auth.py
sc_entsoe/client.py
sc_entsoe/config.py
sc_entsoe/exceptions.py
sc_entsoe/models.py
sc_entsoe/sync_client.py
sc_entsoe/adapters/__init__.py
sc_entsoe/adapters/database/__init__.py
sc_entsoe/adapters/database/postgres.py
sc_entsoe/api/__init__.py
sc_entsoe/api/balancing.py
sc_entsoe/api/generation.py
sc_entsoe/api/hydro.py
sc_entsoe/api/load.py
sc_entsoe/api/network.py
sc_entsoe/api/prices.py
sc_entsoe/api/transmission.py
sc_entsoe/api/unavailability.py
sc_entsoe/core/__init__.py
sc_entsoe/core/env.py
sc_entsoe/core/log.py
sc_entsoe/core/secrets/__init__.py
sc_entsoe/core/secrets/envvar.py
sc_entsoe/core/secrets/secrets.py
sc_entsoe/core/secrets/secretsmanager.py
sc_entsoe/core/utils/__init__.py
sc_entsoe/core/utils/http.py
sc_entsoe/core/utils/maybe.py
sc_entsoe/parsers/__init__.py
sc_entsoe/parsers/converters.py
sc_entsoe/parsers/xml_parser.py
sc_entsoe-0.2.0.dist-info/METADATA
sc_entsoe-0.2.0.dist-info/WHEEL
sc_entsoe-0.2.0.dist-info/licenses/LICENSE
sc_entsoe-0.2.0.dist-info/RECORD
