Metadata-Version: 2.4
Name: sc-entsoe
Version: 0.2.0
Summary: Modern, high-performance Python library for ENTSOE Transparency Platform data
Project-URL: Homepage, https://github.com/skyeenergy/sc-entsoe
Project-URL: Documentation, https://github.com/skyeenergy/sc-entsoe#readme
Project-URL: Repository, https://github.com/skyeenergy/sc-entsoe
Project-URL: Issues, https://github.com/skyeenergy/sc-entsoe/issues
Project-URL: Changelog, https://github.com/skyeenergy/sc-entsoe/releases
Author-email: Skye Energy <developers@skye.energy>
Maintainer-email: Skye Energy <developers@skye.energy>
License: MIT
License-File: LICENSE
Keywords: async,electricity,energy,entsoe,market-data,polars,power,transparency-platform
Classifier: Development Status :: 4 - Beta
Classifier: Intended Audience :: Developers
Classifier: Intended Audience :: Science/Research
Classifier: License :: OSI Approved :: MIT License
Classifier: Operating System :: OS Independent
Classifier: Programming Language :: Python :: 3
Classifier: Programming Language :: Python :: 3.11
Classifier: Programming Language :: Python :: 3.12
Classifier: Programming Language :: Python :: 3.13
Classifier: Programming Language :: Python :: 3.14
Classifier: Topic :: Scientific/Engineering
Classifier: Topic :: Software Development :: Libraries :: Python Modules
Classifier: Typing :: Typed
Requires-Python: >=3.11
Requires-Dist: httpx>=0.27.0
Requires-Dist: pydantic-settings>=2.5.0
Requires-Dist: pydantic>=2.9.0
Requires-Dist: tenacity>=8.2.0
Provides-Extra: dev
Requires-Dist: bandit>=1.7.0; extra == 'dev'
Requires-Dist: lxml-stubs>=0.5.0; extra == 'dev'
Requires-Dist: memory-profiler>=0.61.0; extra == 'dev'
Requires-Dist: mypy>=1.11.0; extra == 'dev'
Requires-Dist: pre-commit>=3.6.0; extra == 'dev'
Requires-Dist: pytest-asyncio>=1.3.0; extra == 'dev'
Requires-Dist: pytest-cov>=7.0.0; extra == 'dev'
Requires-Dist: pytest>=9.0.2; extra == 'dev'
Requires-Dist: ruff>=0.6.0; extra == 'dev'
Provides-Extra: dotenv
Requires-Dist: python-dotenv>=1.0.0; extra == 'dotenv'
Provides-Extra: keyring
Requires-Dist: keyring>=25.0.0; extra == 'keyring'
Provides-Extra: polars
Requires-Dist: polars>=0.20.0; extra == 'polars'
